AssociationEngine/__init__.py
AssociationEngine/Examples/__init__.py
AssociationEngine/Examples/webpage/ReadFromCSV.py
AssociationEngine/Examples/webpage/Server.py
AssociationEngine/Examples/webpage/Subscriber.py
AssociationEngine/Examples/webpage/__init__.py
AssociationEngine/Relationship/Frame.py
AssociationEngine/Relationship/Relationship.py
AssociationEngine/Relationship/SpearframeRelationship.py
AssociationEngine/Relationship/Variable.py
AssociationEngine/Relationship/__init__.py
AssociationEngine/Sensor/Cosine.py
AssociationEngine/Sensor/Sensor.py
AssociationEngine/Sensor/Sine.py
AssociationEngine/Sensor/__init__.py
AssociationEngine/Snapper/AssociationMatrix.py
AssociationEngine/Snapper/Manager.py
AssociationEngine/Snapper/Snapper.py
AssociationEngine/Snapper/__init__.py
association_engine-0.1.4.dist-info/DESCRIPTION.rst
association_engine-0.1.4.dist-info/METADATA
association_engine-0.1.4.dist-info/RECORD
association_engine-0.1.4.dist-info/WHEEL
association_engine-0.1.4.dist-info/metadata.json
association_engine-0.1.4.dist-info/top_level.txt
