Metadata-Version: 2.0
Name: association-engine
Version: 0.1.4
Summary: Correlation values between variables
Home-page: https://github.com/EliCDavis/AssociationEngine
Author: Senior Design Team MSU
Author-email: ecd157@msstate.edu
License: MIT
Keywords: association correlation spearman
Platform: UNKNOWN
Classifier: Development Status :: 3 - Alpha
Classifier: Topic :: Utilities
Classifier: License :: OSI Approved :: MIT License
Requires-Dist: numpy (>=1.12.0,<2.0.0)
Requires-Dist: scipy (<0.19.0,>=0.18.1)
